{
  "unpublishedPage": {
    "name": " Landlord - Apartment Details",
    "slug": "landlord-apartment-details",
    "layouts": [
      {
        "viewMode": false,
        "dsl": {
          "widgetName": "MainContainer",
          "backgroundColor": "none",
          "rightColumn": 1224,
          "snapColumns": 64,
          "detachFromLayout": true,
          "widgetId": "0",
          "topRow": 0,
          "bottomRow": 380,
          "containerStyle": "none",
          "snapRows": 53,
          "parentRowSpace": 1,
          "type": "CANVAS_WIDGET",
          "canExtend": true,
          "version": 77,
          "minHeight": 550,
          "parentColumnSpace": 1,
          "dynamicBindingPathList": [],
          "leftColumn": 0,
          "children": [
            {
              "widgetName": "brand_name",
              "displayName": "Text",
              "iconSVG": "/static/media/icon.97c59b523e6f70ba6f40a10fc2c7c5b5.svg",
              "searchTags": [
                "typography",
                "paragraph",
                "label"
              ],
              "topRow": 0,
              "bottomRow": 4,
              "parentRowSpace": 10,
              "type": "TEXT_WIDGET",
              "hideCard": false,
              "animateLoading": true,
              "overflow": "NONE",
              "fontFamily": "Montserrat",
              "parentColumnSpace": 12.296875,
              "dynamicTriggerPathList": [],
              "leftColumn": 53,
              "dynamicBindingPathList": [
                {
                  "key": "truncateButtonColor"
                },
                {
                  "key": "borderRadius"
                }
              ],
              "shouldTruncate": false,
              "truncateButtonColor": "{{appsmith.theme.colors.primaryColor}}",
              "text": "Average Living",
              "key": "vi8nsa0y8p",
              "isDeprecated": false,
              "rightColumn": 64,
              "textAlign": "LEFT",
              "dynamicHeight": "AUTO_HEIGHT",
              "widgetId": "rdqr2y35r7",
              "minWidth": 450,
              "isVisible": true,
              "fontStyle": "BOLD",
              "textColor": "#7e22ce",
              "version": 1,
              "parentId": "0",
              "renderMode": "CANVAS",
              "isLoading": false,
              "responsiveBehavior": "fill",
              "borderRadius": "{{appsmith.theme.borderRadius.appBorderRadius}}",
              "maxDynamicHeight": 9000,
              "fontSize": "1rem",
              "minDynamicHeight": 4
            },
            {
              "widgetName": "detailed_address",
              "displayName": "Text",
              "iconSVG": "/static/media/icon.97c59b523e6f70ba6f40a10fc2c7c5b5.svg",
              "searchTags": [
                "typography",
                "paragraph",
                "label"
              ],
              "topRow": 4,
              "bottomRow": 8,
              "parentRowSpace": 10,
              "type": "TEXT_WIDGET",
              "hideCard": false,
              "animateLoading": true,
              "overflow": "NONE",
              "fontFamily": "{{appsmith.theme.fontFamily.appFont}}",
              "parentColumnSpace": 12.296875,
              "dynamicTriggerPathList": [],
              "leftColumn": 3,
              "dynamicBindingPathList": [
                {
                  "key": "truncateButtonColor"
                },
                {
                  "key": "fontFamily"
                },
                {
                  "key": "borderRadius"
                }
              ],
              "shouldTruncate": false,
              "truncateButtonColor": "{{appsmith.theme.colors.primaryColor}}",
              "text": "123 Welcome Ave, Boston, MA, 02115",
              "key": "l5jl51o74b",
              "isDeprecated": false,
              "rightColumn": 33,
              "textAlign": "LEFT",
              "dynamicHeight": "AUTO_HEIGHT",
              "widgetId": "tq1uakc3o5",
              "minWidth": 450,
              "isVisible": true,
              "fontStyle": "BOLD",
              "textColor": "#231F20",
              "version": 1,
              "parentId": "0",
              "renderMode": "CANVAS",
              "isLoading": false,
              "responsiveBehavior": "fill",
              "originalTopRow": 2,
              "borderRadius": "{{appsmith.theme.borderRadius.appBorderRadius}}",
              "maxDynamicHeight": 9000,
              "originalBottomRow": 8,
              "fontSize": "1.25rem",
              "minDynamicHeight": 4
            },
            {
              "widgetName": "neighborhood_name",
              "displayName": "Text",
              "iconSVG": "/static/media/icon.97c59b523e6f70ba6f40a10fc2c7c5b5.svg",
              "searchTags": [
                "typography",
                "paragraph",
                "label"
              ],
              "topRow": 8,
              "bottomRow": 12,
              "parentRowSpace": 10,
              "type": "TEXT_WIDGET",
              "hideCard": false,
              "animateLoading": true,
              "overflow": "NONE",
              "fontFamily": "{{appsmith.theme.fontFamily.appFont}}",
              "parentColumnSpace": 12.296875,
              "dynamicTriggerPathList": [],
              "leftColumn": 3,
              "dynamicBindingPathList": [
                {
                  "key": "truncateButtonColor"
                },
                {
                  "key": "fontFamily"
                },
                {
                  "key": "borderRadius"
                }
              ],
              "shouldTruncate": false,
              "truncateButtonColor": "{{appsmith.theme.colors.primaryColor}}",
              "text": "Back Bay",
              "key": "l5jl51o74b",
              "isDeprecated": false,
              "rightColumn": 19,
              "textAlign": "LEFT",
              "dynamicHeight": "AUTO_HEIGHT",
              "widgetId": "okuslgucin",
              "minWidth": 450,
              "isVisible": true,
              "fontStyle": "BOLD",
              "textColor": "#71717a",
              "version": 1,
              "parentId": "0",
              "renderMode": "CANVAS",
              "isLoading": false,
              "responsiveBehavior": "fill",
              "originalTopRow": 57,
              "borderRadius": "{{appsmith.theme.borderRadius.appBorderRadius}}",
              "maxDynamicHeight": 9000,
              "originalBottomRow": 61,
              "fontSize": "1rem",
              "minDynamicHeight": 4
            },
            {
              "boxShadow": "{{appsmith.theme.boxShadow.appBoxShadow}}",
              "widgetName": "apt_1_info",
              "borderColor": "#E0DEDE",
              "isCanvas": true,
              "displayName": "Tabs",
              "iconSVG": "/static/media/icon.74a6d653c8201e66f1cd367a3fba2657.svg",
              "topRow": 14,
              "bottomRow": 33,
              "parentRowSpace": 10,
              "type": "TABS_WIDGET",
              "hideCard": false,
              "shouldScrollContents": true,
              "animateLoading": true,
              "parentColumnSpace": 12.296875,
              "dynamicTriggerPathList": [],
              "leftColumn": 3,
              "dynamicBindingPathList": [
                {
                  "key": "borderRadius"
                },
                {
                  "key": "boxShadow"
                }
              ],
              "children": [
                {
                  "tabId": "tab1",
                  "widgetName": "Canvas1",
                  "displayName": "Canvas",
                  "bottomRow": 180,
                  "topRow": 0,
                  "parentRowSpace": 1,
                  "type": "CANVAS_WIDGET",
                  "canExtend": true,
                  "hideCard": true,
                  "shouldScrollContents": false,
                  "minHeight": 150,
                  "parentColumnSpace": 1,
                  "dynamicTriggerPathList": [],
                  "leftColumn": 0,
                  "dynamicBindingPathList": [],
                  "children": [
                    {
                      "widgetName": "num_bedrooms",
                      "displayName": "Text",
                      "iconSVG": "/static/media/icon.97c59b523e6f70ba6f40a10fc2c7c5b5.svg",
                      "searchTags": [
                        "typography",
                        "paragraph",
                        "label"
                      ],
                      "topRow": 6,
                      "bottomRow": 10,
                      "parentRowSpace": 10,
                      "type": "TEXT_WIDGET",
                      "hideCard": false,
                      "animateLoading": true,
                      "overflow": "NONE",
                      "fontFamily": "{{appsmith.theme.fontFamily.appFont}}",
                      "parentColumnSpace": 11.60009765625,
                      "dynamicTriggerPathList": [],
                      "leftColumn": 11,
                      "dynamicBindingPathList": [
                        {
                          "key": "truncateButtonColor"
                        },
                        {
                          "key": "fontFamily"
                        },
                        {
                          "key": "borderRadius"
                        }
                      ],
                      "shouldTruncate": false,
                      "truncateButtonColor": "{{appsmith.theme.colors.primaryColor}}",
                      "text": "3",
                      "key": "vi8nsa0y8p",
                      "isDeprecated": false,
                      "rightColumn": 17,
                      "textAlign": "LEFT",
                      "dynamicHeight": "AUTO_HEIGHT",
                      "widgetId": "k8xj213zqz",
                      "minWidth": 450,
                      "isVisible": true,
                      "fontStyle": "BOLD",
                      "textColor": "#71717a",
                      "version": 1,
                      "parentId": "cr8lehxf0j",
                      "renderMode": "CANVAS",
                      "isLoading": false,
                      "responsiveBehavior": "fill",
                      "originalTopRow": 6,
                      "borderRadius": "{{appsmith.theme.borderRadius.appBorderRadius}}",
                      "maxDynamicHeight": 9000,
                      "originalBottomRow": 10,
                      "fontSize": "1rem",
                      "minDynamicHeight": 4
                    },
                    {
                      "widgetName": "property_type",
                      "displayName": "Text",
                      "iconSVG": "/static/media/icon.97c59b523e6f70ba6f40a10fc2c7c5b5.svg",
                      "searchTags": [
                        "typography",
                        "paragraph",
                        "label"
                      ],
                      "topRow": 1,
                      "bottomRow": 5,
                      "parentRowSpace": 10,
                      "type": "TEXT_WIDGET",
                      "hideCard": false,
                      "animateLoading": true,
                      "overflow": "NONE",
                      "fontFamily": "{{appsmith.theme.fontFamily.appFont}}",
                      "parentColumnSpace": 11.60009765625,
                      "dynamicTriggerPathList": [],
                      "leftColumn": 2,
                      "dynamicBindingPathList": [
                        {
                          "key": "truncateButtonColor"
                        },
                        {
                          "key": "fontFamily"
                        },
                        {
                          "key": "borderRadius"
                        }
                      ],
                      "shouldTruncate": false,
                      "truncateButtonColor": "{{appsmith.theme.colors.primaryColor}}",
                      "text": "Apartment:",
                      "key": "vi8nsa0y8p",
                      "isDeprecated": false,
                      "rightColumn": 13,
                      "textAlign": "LEFT",
                      "dynamicHeight": "AUTO_HEIGHT",
                      "widgetId": "utfq3nj7qb",
                      "minWidth": 450,
                      "isVisible": true,
                      "fontStyle": "BOLD",
                      "textColor": "#231f20",
                      "version": 1,
                      "parentId": "cr8lehxf0j",
                      "renderMode": "CANVAS",
                      "isLoading": false,
                      "responsiveBehavior": "fill",
                      "originalTopRow": 1,
                      "borderRadius": "{{appsmith.theme.borderRadius.appBorderRadius}}",
                      "maxDynamicHeight": 9000,
                      "originalBottomRow": 5,
                      "fontSize": "1.25rem",
                      "minDynamicHeight": 4
                    },
                    {
                      "widgetName": "bedrooms_labelCopy",
                      "displayName": "Text",
                      "iconSVG": "/static/media/icon.97c59b523e6f70ba6f40a10fc2c7c5b5.svg",
                      "searchTags": [
                        "typography",
                        "paragraph",
                        "label"
                      ],
                      "topRow": 6,
                      "bottomRow": 10,
                      "parentRowSpace": 10,
                      "type": "TEXT_WIDGET",
                      "hideCard": false,
                      "animateLoading": true,
                      "overflow": "NONE",
                      "fontFamily": "{{appsmith.theme.fontFamily.appFont}}",
                      "parentColumnSpace": 11.60009765625,
                      "dynamicTriggerPathList": [],
                      "leftColumn": 2,
                      "dynamicBindingPathList": [
                        {
                          "key": "truncateButtonColor"
                        },
                        {
                          "key": "fontFamily"
                        },
                        {
                          "key": "borderRadius"
                        }
                      ],
                      "shouldTruncate": false,
                      "truncateButtonColor": "{{appsmith.theme.colors.primaryColor}}",
                      "text": "Bedrooms:",
                      "key": "vi8nsa0y8p",
                      "isDeprecated": false,
                      "rightColumn": 11,
                      "textAlign": "LEFT",
                      "dynamicHeight": "AUTO_HEIGHT",
                      "widgetId": "2kq2uxvv5a",
                      "minWidth": 450,
                      "isVisible": true,
                      "fontStyle": "BOLD",
                      "textColor": "#231f20#7e22ce",
                      "version": 1,
                      "parentId": "cr8lehxf0j",
                      "renderMode": "CANVAS",
                      "isLoading": false,
                      "responsiveBehavior": "fill",
                      "originalTopRow": 6,
                      "borderRadius": "{{appsmith.theme.borderRadius.appBorderRadius}}",
                      "maxDynamicHeight": 9000,
                      "originalBottomRow": 10,
                      "fontSize": "1rem",
                      "minDynamicHeight": 4
                    },
                    {
                      "widgetName": "bathrooms_label",
                      "displayName": "Text",
                      "iconSVG": "/static/media/icon.97c59b523e6f70ba6f40a10fc2c7c5b5.svg",
                      "searchTags": [
                        "typography",
                        "paragraph",
                        "label"
                      ],
                      "topRow": 10,
                      "bottomRow": 14,
                      "parentRowSpace": 10,
                      "type": "TEXT_WIDGET",
                      "hideCard": false,
                      "animateLoading": true,
                      "overflow": "NONE",
                      "fontFamily": "{{appsmith.theme.fontFamily.appFont}}",
                      "parentColumnSpace": 11.60009765625,
                      "dynamicTriggerPathList": [],
                      "leftColumn": 2,
                      "dynamicBindingPathList": [
                        {
                          "key": "truncateButtonColor"
                        },
                        {
                          "key": "fontFamily"
                        },
                        {
                          "key": "borderRadius"
                        }
                      ],
                      "shouldTruncate": false,
                      "truncateButtonColor": "{{appsmith.theme.colors.primaryColor}}",
                      "text": "Bathrooms:",
                      "key": "vi8nsa0y8p",
                      "isDeprecated": false,
                      "rightColumn": 11,
                      "textAlign": "LEFT",
                      "dynamicHeight": "AUTO_HEIGHT",
                      "widgetId": "ab1pci2l77",
                      "minWidth": 450,
                      "isVisible": true,
                      "fontStyle": "BOLD",
                      "textColor": "#231F20",
                      "version": 1,
                      "parentId": "cr8lehxf0j",
                      "renderMode": "CANVAS",
                      "isLoading": false,
                      "responsiveBehavior": "fill",
                      "originalTopRow": 10,
                      "borderRadius": "{{appsmith.theme.borderRadius.appBorderRadius}}",
                      "maxDynamicHeight": 9000,
                      "originalBottomRow": 14,
                      "fontSize": "1rem",
                      "minDynamicHeight": 4
                    },
                    {
                      "widgetName": "sq_ft_label",
                      "displayName": "Text",
                      "iconSVG": "/static/media/icon.97c59b523e6f70ba6f40a10fc2c7c5b5.svg",
                      "searchTags": [
                        "typography",
                        "paragraph",
                        "label"
                      ],
                      "topRow": 14,
                      "bottomRow": 18,
                      "parentRowSpace": 10,
                      "type": "TEXT_WIDGET",
                      "hideCard": false,
                      "animateLoading": true,
                      "overflow": "NONE",
                      "fontFamily": "{{appsmith.theme.fontFamily.appFont}}",
                      "parentColumnSpace": 11.60009765625,
                      "dynamicTriggerPathList": [],
                      "leftColumn": 2,
                      "dynamicBindingPathList": [
                        {
                          "key": "truncateButtonColor"
                        },
                        {
                          "key": "fontFamily"
                        },
                        {
                          "key": "borderRadius"
                        }
                      ],
                      "shouldTruncate": false,
                      "truncateButtonColor": "{{appsmith.theme.colors.primaryColor}}",
                      "text": "Square Feet:",
                      "key": "vi8nsa0y8p",
                      "isDeprecated": false,
                      "rightColumn": 12,
                      "textAlign": "LEFT",
                      "dynamicHeight": "AUTO_HEIGHT",
                      "widgetId": "8nlgb3u0yo",
                      "minWidth": 450,
                      "isVisible": true,
                      "fontStyle": "BOLD",
                      "textColor": "#231F20",
                      "version": 1,
                      "parentId": "cr8lehxf0j",
                      "renderMode": "CANVAS",
                      "isLoading": false,
                      "responsiveBehavior": "fill",
                      "originalTopRow": 14,
                      "borderRadius": "{{appsmith.theme.borderRadius.appBorderRadius}}",
                      "maxDynamicHeight": 9000,
                      "originalBottomRow": 18,
                      "fontSize": "1rem",
                      "minDynamicHeight": 4
                    },
                    {
                      "widgetName": "lease_start_date_label",
                      "displayName": "Text",
                      "iconSVG": "/static/media/icon.97c59b523e6f70ba6f40a10fc2c7c5b5.svg",
                      "searchTags": [
                        "typography",
                        "paragraph",
                        "label"
                      ],
                      "topRow": 6,
                      "bottomRow": 10,
                      "parentRowSpace": 10,
                      "type": "TEXT_WIDGET",
                      "hideCard": false,
                      "animateLoading": true,
                      "overflow": "NONE",
                      "fontFamily": "{{appsmith.theme.fontFamily.appFont}}",
                      "parentColumnSpace": 11.60009765625,
                      "dynamicTriggerPathList": [],
                      "leftColumn": 24,
                      "dynamicBindingPathList": [
                        {
                          "key": "truncateButtonColor"
                        },
                        {
                          "key": "fontFamily"
                        },
                        {
                          "key": "borderRadius"
                        }
                      ],
                      "shouldTruncate": false,
                      "truncateButtonColor": "{{appsmith.theme.colors.primaryColor}}",
                      "text": "Lease Start:",
                      "key": "vi8nsa0y8p",
                      "isDeprecated": false,
                      "rightColumn": 33,
                      "textAlign": "LEFT",
                      "dynamicHeight": "AUTO_HEIGHT",
                      "widgetId": "w1zet5ytpb",
                      "minWidth": 450,
                      "isVisible": true,
                      "fontStyle": "BOLD",
                      "textColor": "#231F20",
                      "version": 1,
                      "parentId": "cr8lehxf0j",
                      "renderMode": "CANVAS",
                      "isLoading": false,
                      "responsiveBehavior": "fill",
                      "originalTopRow": 6,
                      "borderRadius": "{{appsmith.theme.borderRadius.appBorderRadius}}",
                      "maxDynamicHeight": 9000,
                      "originalBottomRow": 11,
                      "fontSize": "1rem",
                      "minDynamicHeight": 4
                    },
                    {
                      "widgetName": "lease_end_date_label",
                      "displayName": "Text",
                      "iconSVG": "/static/media/icon.97c59b523e6f70ba6f40a10fc2c7c5b5.svg",
                      "searchTags": [
                        "typography",
                        "paragraph",
                        "label"
                      ],
                      "topRow": 10,
                      "bottomRow": 14,
                      "parentRowSpace": 10,
                      "type": "TEXT_WIDGET",
                      "hideCard": false,
                      "animateLoading": true,
                      "overflow": "NONE",
                      "fontFamily": "{{appsmith.theme.fontFamily.appFont}}",
                      "parentColumnSpace": 11.60009765625,
                      "dynamicTriggerPathList": [],
                      "leftColumn": 24,
                      "dynamicBindingPathList": [
                        {
                          "key": "truncateButtonColor"
                        },
                        {
                          "key": "fontFamily"
                        },
                        {
                          "key": "borderRadius"
                        }
                      ],
                      "shouldTruncate": false,
                      "truncateButtonColor": "{{appsmith.theme.colors.primaryColor}}",
                      "text": "Lease End:",
                      "key": "vi8nsa0y8p",
                      "isDeprecated": false,
                      "rightColumn": 33,
                      "textAlign": "LEFT",
                      "dynamicHeight": "AUTO_HEIGHT",
                      "widgetId": "ay80kknhn4",
                      "minWidth": 450,
                      "isVisible": true,
                      "fontStyle": "BOLD",
                      "textColor": "#231F20",
                      "version": 1,
                      "parentId": "cr8lehxf0j",
                      "renderMode": "CANVAS",
                      "isLoading": false,
                      "responsiveBehavior": "fill",
                      "originalTopRow": 10,
                      "borderRadius": "{{appsmith.theme.borderRadius.appBorderRadius}}",
                      "maxDynamicHeight": 9000,
                      "originalBottomRow": 14,
                      "fontSize": "1rem",
                      "minDynamicHeight": 4
                    },
                    {
                      "widgetName": "lease_start_date",
                      "displayName": "Text",
                      "iconSVG": "/static/media/icon.97c59b523e6f70ba6f40a10fc2c7c5b5.svg",
                      "searchTags": [
                        "typography",
                        "paragraph",
                        "label"
                      ],
                      "topRow": 6,
                      "bottomRow": 10,
                      "parentRowSpace": 10,
                      "type": "TEXT_WIDGET",
                      "hideCard": false,
                      "animateLoading": true,
                      "overflow": "NONE",
                      "fontFamily": "{{appsmith.theme.fontFamily.appFont}}",
                      "parentColumnSpace": 11.60009765625,
                      "dynamicTriggerPathList": [],
                      "leftColumn": 33,
                      "dynamicBindingPathList": [
                        {
                          "key": "truncateButtonColor"
                        },
                        {
                          "key": "fontFamily"
                        },
                        {
                          "key": "borderRadius"
                        }
                      ],
                      "shouldTruncate": false,
                      "truncateButtonColor": "{{appsmith.theme.colors.primaryColor}}",
                      "text": "9/1/23",
                      "key": "vi8nsa0y8p",
                      "isDeprecated": false,
                      "rightColumn": 39,
                      "textAlign": "LEFT",
                      "dynamicHeight": "AUTO_HEIGHT",
                      "widgetId": "x6wvpwwomk",
                      "minWidth": 450,
                      "isVisible": true,
                      "fontStyle": "BOLD",
                      "textColor": "#71717a",
                      "version": 1,
                      "parentId": "cr8lehxf0j",
                      "renderMode": "CANVAS",
                      "isLoading": false,
                      "responsiveBehavior": "fill",
                      "originalTopRow": 6,
                      "borderRadius": "{{appsmith.theme.borderRadius.appBorderRadius}}",
                      "maxDynamicHeight": 9000,
                      "originalBottomRow": 10,
                      "fontSize": "1rem",
                      "minDynamicHeight": 4
                    },
                    {
                      "widgetName": "lease_end_date",
                      "displayName": "Text",
                      "iconSVG": "/static/media/icon.97c59b523e6f70ba6f40a10fc2c7c5b5.svg",
                      "searchTags": [
                        "typography",
                        "paragraph",
                        "label"
                      ],
                      "topRow": 10,
                      "bottomRow": 14,
                      "parentRowSpace": 10,
                      "type": "TEXT_WIDGET",
                      "hideCard": false,
                      "animateLoading": true,
                      "overflow": "NONE",
                      "fontFamily": "{{appsmith.theme.fontFamily.appFont}}",
                      "parentColumnSpace": 11.60009765625,
                      "dynamicTriggerPathList": [],
                      "leftColumn": 33,
                      "dynamicBindingPathList": [
                        {
                          "key": "truncateButtonColor"
                        },
                        {
                          "key": "fontFamily"
                        },
                        {
                          "key": "borderRadius"
                        }
                      ],
                      "shouldTruncate": false,
                      "truncateButtonColor": "{{appsmith.theme.colors.primaryColor}}",
                      "text": "8/31/24",
                      "key": "vi8nsa0y8p",
                      "isDeprecated": false,
                      "rightColumn": 40,
                      "textAlign": "LEFT",
                      "dynamicHeight": "AUTO_HEIGHT",
                      "widgetId": "h48oqm73wr",
                      "minWidth": 450,
                      "isVisible": true,
                      "fontStyle": "BOLD",
                      "textColor": "#71717a",
                      "version": 1,
                      "parentId": "cr8lehxf0j",
                      "renderMode": "CANVAS",
                      "isLoading": false,
                      "responsiveBehavior": "fill",
                      "originalTopRow": 10,
                      "borderRadius": "{{appsmith.theme.borderRadius.appBorderRadius}}",
                      "maxDynamicHeight": 9000,
                      "originalBottomRow": 15,
                      "fontSize": "1rem",
                      "minDynamicHeight": 4
                    },
                    {
                      "widgetName": "num_bathrooms",
                      "displayName": "Text",
                      "iconSVG": "/static/media/icon.97c59b523e6f70ba6f40a10fc2c7c5b5.svg",
                      "searchTags": [
                        "typography",
                        "paragraph",
                        "label"
                      ],
                      "topRow": 10,
                      "bottomRow": 14,
                      "parentRowSpace": 10,
                      "type": "TEXT_WIDGET",
                      "hideCard": false,
                      "animateLoading": true,
                      "overflow": "NONE",
                      "fontFamily": "{{appsmith.theme.fontFamily.appFont}}",
                      "parentColumnSpace": 11.60009765625,
                      "dynamicTriggerPathList": [],
                      "leftColumn": 11,
                      "dynamicBindingPathList": [
                        {
                          "key": "truncateButtonColor"
                        },
                        {
                          "key": "fontFamily"
                        },
                        {
                          "key": "borderRadius"
                        }
                      ],
                      "shouldTruncate": false,
                      "truncateButtonColor": "{{appsmith.theme.colors.primaryColor}}",
                      "text": "1\n",
                      "key": "vi8nsa0y8p",
                      "isDeprecated": false,
                      "rightColumn": 17,
                      "textAlign": "LEFT",
                      "dynamicHeight": "AUTO_HEIGHT",
                      "widgetId": "suc8p8s8uk",
                      "minWidth": 450,
                      "isVisible": true,
                      "fontStyle": "BOLD",
                      "textColor": "#71717a",
                      "version": 1,
                      "parentId": "cr8lehxf0j",
                      "renderMode": "CANVAS",
                      "isLoading": false,
                      "responsiveBehavior": "fill",
                      "originalTopRow": 10,
                      "borderRadius": "{{appsmith.theme.borderRadius.appBorderRadius}}",
                      "maxDynamicHeight": 9000,
                      "originalBottomRow": 14,
                      "fontSize": "1rem",
                      "minDynamicHeight": 4
                    },
                    {
                      "widgetName": "num_sq_ft",
                      "displayName": "Text",
                      "iconSVG": "/static/media/icon.97c59b523e6f70ba6f40a10fc2c7c5b5.svg",
                      "searchTags": [
                        "typography",
                        "paragraph",
                        "label"
                      ],
                      "topRow": 14,
                      "bottomRow": 18,
                      "parentRowSpace": 10,
                      "type": "TEXT_WIDGET",
                      "hideCard": false,
                      "animateLoading": true,
                      "overflow": "NONE",
                      "fontFamily": "{{appsmith.theme.fontFamily.appFont}}",
                      "parentColumnSpace": 11.60009765625,
                      "dynamicTriggerPathList": [],
                      "leftColumn": 12,
                      "dynamicBindingPathList": [
                        {
                          "key": "truncateButtonColor"
                        },
                        {
                          "key": "fontFamily"
                        },
                        {
                          "key": "borderRadius"
                        }
                      ],
                      "shouldTruncate": false,
                      "truncateButtonColor": "{{appsmith.theme.colors.primaryColor}}",
                      "text": "800",
                      "key": "vi8nsa0y8p",
                      "isDeprecated": false,
                      "rightColumn": 18,
                      "textAlign": "LEFT",
                      "dynamicHeight": "AUTO_HEIGHT",
                      "widgetId": "v2wirfvc39",
                      "minWidth": 450,
                      "isVisible": true,
                      "fontStyle": "BOLD",
                      "textColor": "#71717a",
                      "version": 1,
                      "parentId": "cr8lehxf0j",
                      "renderMode": "CANVAS",
                      "isLoading": false,
                      "responsiveBehavior": "fill",
                      "originalTopRow": 14,
                      "borderRadius": "{{appsmith.theme.borderRadius.appBorderRadius}}",
                      "maxDynamicHeight": 9000,
                      "originalBottomRow": 18,
                      "fontSize": "1rem",
                      "minDynamicHeight": 4
                    },
                    {
                      "widgetName": "rent_price",
                      "displayName": "Text",
                      "iconSVG": "/static/media/icon.97c59b523e6f70ba6f40a10fc2c7c5b5.svg",
                      "searchTags": [
                        "typography",
                        "paragraph",
                        "label"
                      ],
                      "topRow": 1,
                      "bottomRow": 5,
                      "parentRowSpace": 10,
                      "type": "TEXT_WIDGET",
                      "hideCard": false,
                      "animateLoading": true,
                      "overflow": "NONE",
                      "fontFamily": "{{appsmith.theme.fontFamily.appFont}}",
                      "parentColumnSpace": 11.60009765625,
                      "dynamicTriggerPathList": [],
                      "leftColumn": 13,
                      "dynamicBindingPathList": [
                        {
                          "key": "truncateButtonColor"
                        },
                        {
                          "key": "fontFamily"
                        },
                        {
                          "key": "borderRadius"
                        }
                      ],
                      "shouldTruncate": false,
                      "truncateButtonColor": "{{appsmith.theme.colors.primaryColor}}",
                      "text": "$4000",
                      "key": "vi8nsa0y8p",
                      "isDeprecated": false,
                      "rightColumn": 20,
                      "textAlign": "LEFT",
                      "dynamicHeight": "AUTO_HEIGHT",
                      "widgetId": "igiavvu7or",
                      "minWidth": 450,
                      "isVisible": true,
                      "fontStyle": "BOLD",
                      "textColor": "#7e22ce",
                      "version": 1,
                      "parentId": "cr8lehxf0j",
                      "renderMode": "CANVAS",
                      "isLoading": false,
                      "responsiveBehavior": "fill",
                      "originalTopRow": 1,
                      "borderRadius": "{{appsmith.theme.borderRadius.appBorderRadius}}",
                      "maxDynamicHeight": 9000,
                      "originalBottomRow": 5,
                      "fontSize": "1.25rem",
                      "minDynamicHeight": 4
                    }
                  ],
                  "isDisabled": false,
                  "key": "23t0u795pv",
                  "isDeprecated": false,
                  "tabName": "Overview",
                  "rightColumn": 295.125,
                  "detachFromLayout": true,
                  "widgetId": "cr8lehxf0j",
                  "minWidth": 450,
                  "isVisible": true,
                  "version": 1,
                  "parentId": "rnxapq94an",
                  "renderMode": "CANVAS",
                  "isLoading": false,
                  "responsiveBehavior": "fill",
                  "flexLayers": []
                },
                {
                  "tabId": "tab4i4to3lr5y",
                  "widgetName": "Canvas3",
                  "displayName": "Canvas",
                  "topRow": 1,
                  "bottomRow": 150,
                  "parentRowSpace": 1,
                  "type": "CANVAS_WIDGET",
                  "canExtend": false,
                  "hideCard": true,
                  "minHeight": 190,
                  "parentColumnSpace": 1,
                  "dynamicTriggerPathList": [],
                  "leftColumn": 0,
                  "dynamicBindingPathList": [],
                  "children": [
                    {
                      "widgetName": "market_price_label",
                      "displayName": "Text",
                      "iconSVG": "/static/media/icon.97c59b523e6f70ba6f40a10fc2c7c5b5.svg",
                      "searchTags": [
                        "typography",
                        "paragraph",
                        "label"
                      ],
                      "topRow": 2,
                      "bottomRow": 6,
                      "parentRowSpace": 10,
                      "type": "TEXT_WIDGET",
                      "hideCard": false,
                      "animateLoading": true,
                      "overflow": "NONE",
                      "fontFamily": "{{appsmith.theme.fontFamily.appFont}}",
                      "parentColumnSpace": 10.83154296875,
                      "dynamicTriggerPathList": [],
                      "leftColumn": 1,
                      "dynamicBindingPathList": [
                        {
                          "key": "truncateButtonColor"
                        },
                        {
                          "key": "fontFamily"
                        },
                        {
                          "key": "borderRadius"
                        }
                      ],
                      "shouldTruncate": false,
                      "truncateButtonColor": "{{appsmith.theme.colors.primaryColor}}",
                      "text": "Market Price:",
                      "key": "vi8nsa0y8p",
                      "isDeprecated": false,
                      "rightColumn": 11,
                      "textAlign": "LEFT",
                      "dynamicHeight": "AUTO_HEIGHT",
                      "widgetId": "279mruo302",
                      "minWidth": 450,
                      "isVisible": true,
                      "fontStyle": "BOLD",
                      "textColor": "#231F20",
                      "version": 1,
                      "parentId": "r4kjenj77t",
                      "renderMode": "CANVAS",
                      "isLoading": false,
                      "responsiveBehavior": "fill",
                      "borderRadius": "{{appsmith.theme.borderRadius.appBorderRadius}}",
                      "maxDynamicHeight": 9000,
                      "fontSize": "1rem",
                      "minDynamicHeight": 4
                    },
                    {
                      "widgetName": "market_price_labelCopy",
                      "displayName": "Text",
                      "iconSVG": "/static/media/icon.97c59b523e6f70ba6f40a10fc2c7c5b5.svg",
                      "searchTags": [
                        "typography",
                        "paragraph",
                        "label"
                      ],
                      "topRow": 2,
                      "bottomRow": 6,
                      "parentRowSpace": 10,
                      "type": "TEXT_WIDGET",
                      "hideCard": false,
                      "animateLoading": true,
                      "overflow": "NONE",
                      "fontFamily": "{{appsmith.theme.fontFamily.appFont}}",
                      "parentColumnSpace": 10.83154296875,
                      "dynamicTriggerPathList": [],
                      "leftColumn": 11,
                      "dynamicBindingPathList": [
                        {
                          "key": "truncateButtonColor"
                        },
                        {
                          "key": "fontFamily"
                        },
                        {
                          "key": "borderRadius"
                        }
                      ],
                      "shouldTruncate": false,
                      "truncateButtonColor": "{{appsmith.theme.colors.primaryColor}}",
                      "text": "$3800",
                      "key": "vi8nsa0y8p",
                      "isDeprecated": false,
                      "rightColumn": 21,
                      "textAlign": "LEFT",
                      "dynamicHeight": "AUTO_HEIGHT",
                      "widgetId": "3t3bf8apea",
                      "minWidth": 450,
                      "isVisible": true,
                      "fontStyle": "BOLD",
                      "textColor": "#71717a",
                      "version": 1,
                      "parentId": "r4kjenj77t",
                      "renderMode": "CANVAS",
                      "isLoading": false,
                      "responsiveBehavior": "fill",
                      "borderRadius": "{{appsmith.theme.borderRadius.appBorderRadius}}",
                      "maxDynamicHeight": 9000,
                      "fontSize": "1rem",
                      "minDynamicHeight": 4
                    }
                  ],
                  "key": "23t0u795pv",
                  "isDeprecated": false,
                  "tabName": "Market Price",
                  "rightColumn": 762.40625,
                  "detachFromLayout": true,
                  "widgetId": "r4kjenj77t",
                  "containerStyle": "none",
                  "minWidth": 450,
                  "isVisible": true,
                  "version": 1,
                  "parentId": "rnxapq94an",
                  "renderMode": "CANVAS",
                  "isLoading": false,
                  "responsiveBehavior": "fill",
                  "flexLayers": []
                },
                {
                  "tabId": "tab00emm8idc2",
                  "widgetName": "Canvas4",
                  "displayName": "Canvas",
                  "topRow": 1,
                  "bottomRow": 150,
                  "parentRowSpace": 1,
                  "type": "CANVAS_WIDGET",
                  "canExtend": false,
                  "hideCard": true,
                  "minHeight": 190,
                  "parentColumnSpace": 1,
                  "dynamicTriggerPathList": [],
                  "leftColumn": 0,
                  "dynamicBindingPathList": [],
                  "children": [
                    {
                      "widgetName": "neighborhood_nickname",
                      "displayName": "Text",
                      "iconSVG": "/static/media/icon.97c59b523e6f70ba6f40a10fc2c7c5b5.svg",
                      "searchTags": [
                        "typography",
                        "paragraph",
                        "label"
                      ],
                      "topRow": 1,
                      "bottomRow": 5,
                      "parentRowSpace": 10,
                      "type": "TEXT_WIDGET",
                      "hideCard": false,
                      "animateLoading": true,
                      "overflow": "NONE",
                      "fontFamily": "{{appsmith.theme.fontFamily.appFont}}",
                      "parentColumnSpace": 10.83154296875,
                      "dynamicTriggerPathList": [],
                      "leftColumn": 1,
                      "dynamicBindingPathList": [
                        {
                          "key": "truncateButtonColor"
                        },
                        {
                          "key": "fontFamily"
                        },
                        {
                          "key": "borderRadius"
                        }
                      ],
                      "shouldTruncate": false,
                      "truncateButtonColor": "{{appsmith.theme.colors.primaryColor}}",
                      "text": "Middlesex",
                      "key": "vi8nsa0y8p",
                      "isDeprecated": false,
                      "rightColumn": 17,
                      "textAlign": "LEFT",
                      "dynamicHeight": "AUTO_HEIGHT",
                      "widgetId": "0z5byakyj9",
                      "minWidth": 450,
                      "isVisible": true,
                      "fontStyle": "BOLD",
                      "textColor": "#231F20",
                      "version": 1,
                      "parentId": "ae8b37mkc3",
                      "renderMode": "CANVAS",
                      "isLoading": false,
                      "responsiveBehavior": "fill",
                      "borderRadius": "{{appsmith.theme.borderRadius.appBorderRadius}}",
                      "maxDynamicHeight": 9000,
                      "fontSize": "1.25rem",
                      "minDynamicHeight": 4
                    },
                    {
                      "widgetName": "num_schools_label",
                      "displayName": "Text",
                      "iconSVG": "/static/media/icon.97c59b523e6f70ba6f40a10fc2c7c5b5.svg",
                      "searchTags": [
                        "typography",
                        "paragraph",
                        "label"
                      ],
                      "topRow": 5,
                      "bottomRow": 9,
                      "parentRowSpace": 10,
                      "type": "TEXT_WIDGET",
                      "hideCard": false,
                      "animateLoading": true,
                      "overflow": "NONE",
                      "fontFamily": "{{appsmith.theme.fontFamily.appFont}}",
                      "parentColumnSpace": 10.83154296875,
                      "dynamicTriggerPathList": [],
                      "leftColumn": 1,
                      "dynamicBindingPathList": [
                        {
                          "key": "truncateButtonColor"
                        },
                        {
                          "key": "fontFamily"
                        },
                        {
                          "key": "borderRadius"
                        }
                      ],
                      "shouldTruncate": false,
                      "truncateButtonColor": "{{appsmith.theme.colors.primaryColor}}",
                      "text": "Number of Schools:",
                      "key": "vi8nsa0y8p",
                      "isDeprecated": false,
                      "rightColumn": 16,
                      "textAlign": "LEFT",
                      "dynamicHeight": "AUTO_HEIGHT",
                      "widgetId": "us2fidal3k",
                      "minWidth": 450,
                      "isVisible": true,
                      "fontStyle": "BOLD",
                      "textColor": "#231F20",
                      "version": 1,
                      "parentId": "ae8b37mkc3",
                      "renderMode": "CANVAS",
                      "isLoading": false,
                      "responsiveBehavior": "fill",
                      "originalTopRow": 5,
                      "borderRadius": "{{appsmith.theme.borderRadius.appBorderRadius}}",
                      "maxDynamicHeight": 9000,
                      "originalBottomRow": 9,
                      "fontSize": "1rem",
                      "minDynamicHeight": 4
                    },
                    {
                      "widgetName": "walkability_label",
                      "displayName": "Text",
                      "iconSVG": "/static/media/icon.97c59b523e6f70ba6f40a10fc2c7c5b5.svg",
                      "searchTags": [
                        "typography",
                        "paragraph",
                        "label"
                      ],
                      "topRow": 9,
                      "bottomRow": 13,
                      "parentRowSpace": 10,
                      "type": "TEXT_WIDGET",
                      "hideCard": false,
                      "animateLoading": true,
                      "overflow": "NONE",
                      "fontFamily": "{{appsmith.theme.fontFamily.appFont}}",
                      "parentColumnSpace": 10.83154296875,
                      "dynamicTriggerPathList": [],
                      "leftColumn": 1,
                      "dynamicBindingPathList": [
                        {
                          "key": "truncateButtonColor"
                        },
                        {
                          "key": "fontFamily"
                        },
                        {
                          "key": "borderRadius"
                        }
                      ],
                      "shouldTruncate": false,
                      "truncateButtonColor": "{{appsmith.theme.colors.primaryColor}}",
                      "text": "Walkability:",
                      "key": "vi8nsa0y8p",
                      "isDeprecated": false,
                      "rightColumn": 10,
                      "textAlign": "LEFT",
                      "dynamicHeight": "AUTO_HEIGHT",
                      "widgetId": "y86z6bkpfa",
                      "minWidth": 450,
                      "isVisible": true,
                      "fontStyle": "BOLD",
                      "textColor": "#231F20",
                      "version": 1,
                      "parentId": "ae8b37mkc3",
                      "renderMode": "CANVAS",
                      "isLoading": false,
                      "responsiveBehavior": "fill",
                      "originalTopRow": 5,
                      "borderRadius": "{{appsmith.theme.borderRadius.appBorderRadius}}",
                      "maxDynamicHeight": 9000,
                      "originalBottomRow": 9,
                      "fontSize": "1rem",
                      "minDynamicHeight": 4
                    },
                    {
                      "widgetName": "cost_sq_ft_label",
                      "displayName": "Text",
                      "iconSVG": "/static/media/icon.97c59b523e6f70ba6f40a10fc2c7c5b5.svg",
                      "searchTags": [
                        "typography",
                        "paragraph",
                        "label"
                      ],
                      "topRow": 5,
                      "bottomRow": 9,
                      "parentRowSpace": 10,
                      "type": "TEXT_WIDGET",
                      "hideCard": false,
                      "animateLoading": true,
                      "overflow": "NONE",
                      "fontFamily": "{{appsmith.theme.fontFamily.appFont}}",
                      "parentColumnSpace": 10.83154296875,
                      "dynamicTriggerPathList": [],
                      "leftColumn": 26,
                      "dynamicBindingPathList": [
                        {
                          "key": "truncateButtonColor"
                        },
                        {
                          "key": "fontFamily"
                        },
                        {
                          "key": "borderRadius"
                        }
                      ],
                      "shouldTruncate": false,
                      "truncateButtonColor": "{{appsmith.theme.colors.primaryColor}}",
                      "text": "Cost Per Square Foot:",
                      "key": "vi8nsa0y8p",
                      "isDeprecated": false,
                      "rightColumn": 42,
                      "textAlign": "LEFT",
                      "dynamicHeight": "AUTO_HEIGHT",
                      "widgetId": "p6yn5exgz4",
                      "minWidth": 450,
                      "isVisible": true,
                      "fontStyle": "BOLD",
                      "textColor": "#231F20",
                      "version": 1,
                      "parentId": "ae8b37mkc3",
                      "renderMode": "CANVAS",
                      "isLoading": false,
                      "responsiveBehavior": "fill",
                      "originalTopRow": 5,
                      "borderRadius": "{{appsmith.theme.borderRadius.appBorderRadius}}",
                      "maxDynamicHeight": 9000,
                      "originalBottomRow": 12,
                      "fontSize": "1rem",
                      "minDynamicHeight": 4
                    },
                    {
                      "widgetName": "appreciation_label",
                      "displayName": "Text",
                      "iconSVG": "/static/media/icon.97c59b523e6f70ba6f40a10fc2c7c5b5.svg",
                      "searchTags": [
                        "typography",
                        "paragraph",
                        "label"
                      ],
                      "topRow": 9,
                      "bottomRow": 13,
                      "parentRowSpace": 10,
                      "type": "TEXT_WIDGET",
                      "hideCard": false,
                      "animateLoading": true,
                      "overflow": "NONE",
                      "fontFamily": "{{appsmith.theme.fontFamily.appFont}}",
                      "parentColumnSpace": 10.83154296875,
                      "dynamicTriggerPathList": [],
                      "leftColumn": 26,
                      "dynamicBindingPathList": [
                        {
                          "key": "truncateButtonColor"
                        },
                        {
                          "key": "fontFamily"
                        },
                        {
                          "key": "borderRadius"
                        }
                      ],
                      "shouldTruncate": false,
                      "truncateButtonColor": "{{appsmith.theme.colors.primaryColor}}",
                      "text": "Appreciation:",
                      "key": "vi8nsa0y8p",
                      "isDeprecated": false,
                      "rightColumn": 36,
                      "textAlign": "LEFT",
                      "dynamicHeight": "AUTO_HEIGHT",
                      "widgetId": "5x1tk6b1t6",
                      "minWidth": 450,
                      "isVisible": true,
                      "fontStyle": "BOLD",
                      "textColor": "#231F20",
                      "version": 1,
                      "parentId": "ae8b37mkc3",
                      "renderMode": "CANVAS",
                      "isLoading": false,
                      "responsiveBehavior": "fill",
                      "originalTopRow": 5,
                      "borderRadius": "{{appsmith.theme.borderRadius.appBorderRadius}}",
                      "maxDynamicHeight": 9000,
                      "originalBottomRow": 12,
                      "fontSize": "1rem",
                      "minDynamicHeight": 4
                    },
                    {
                      "widgetName": "num_schools",
                      "displayName": "Text",
                      "iconSVG": "/static/media/icon.97c59b523e6f70ba6f40a10fc2c7c5b5.svg",
                      "searchTags": [
                        "typography",
                        "paragraph",
                        "label"
                      ],
                      "topRow": 5,
                      "bottomRow": 9,
                      "parentRowSpace": 10,
                      "type": "TEXT_WIDGET",
                      "hideCard": false,
                      "animateLoading": true,
                      "overflow": "NONE",
                      "fontFamily": "{{appsmith.theme.fontFamily.appFont}}",
                      "parentColumnSpace": 10.83154296875,
                      "dynamicTriggerPathList": [],
                      "leftColumn": 16,
                      "dynamicBindingPathList": [
                        {
                          "key": "truncateButtonColor"
                        },
                        {
                          "key": "fontFamily"
                        },
                        {
                          "key": "borderRadius"
                        }
                      ],
                      "shouldTruncate": false,
                      "truncateButtonColor": "{{appsmith.theme.colors.primaryColor}}",
                      "text": "10",
                      "key": "vi8nsa0y8p",
                      "isDeprecated": false,
                      "rightColumn": 19,
                      "textAlign": "LEFT",
                      "dynamicHeight": "AUTO_HEIGHT",
                      "widgetId": "ix8ber3pxt",
                      "minWidth": 450,
                      "isVisible": true,
                      "fontStyle": "BOLD",
                      "textColor": "#71717a",
                      "version": 1,
                      "parentId": "ae8b37mkc3",
                      "renderMode": "CANVAS",
                      "isLoading": false,
                      "responsiveBehavior": "fill",
                      "originalTopRow": 5,
                      "borderRadius": "{{appsmith.theme.borderRadius.appBorderRadius}}",
                      "maxDynamicHeight": 9000,
                      "originalBottomRow": 9,
                      "fontSize": "1rem",
                      "minDynamicHeight": 4
                    },
                    {
                      "widgetName": "walkability",
                      "displayName": "Text",
                      "iconSVG": "/static/media/icon.97c59b523e6f70ba6f40a10fc2c7c5b5.svg",
                      "searchTags": [
                        "typography",
                        "paragraph",
                        "label"
                      ],
                      "topRow": 9,
                      "bottomRow": 13,
                      "parentRowSpace": 10,
                      "type": "TEXT_WIDGET",
                      "hideCard": false,
                      "animateLoading": true,
                      "overflow": "NONE",
                      "fontFamily": "{{appsmith.theme.fontFamily.appFont}}",
                      "parentColumnSpace": 10.83154296875,
                      "dynamicTriggerPathList": [],
                      "leftColumn": 11,
                      "dynamicBindingPathList": [
                        {
                          "key": "truncateButtonColor"
                        },
                        {
                          "key": "fontFamily"
                        },
                        {
                          "key": "borderRadius"
                        }
                      ],
                      "shouldTruncate": false,
                      "truncateButtonColor": "{{appsmith.theme.colors.primaryColor}}",
                      "text": "Label",
                      "key": "vi8nsa0y8p",
                      "isDeprecated": false,
                      "rightColumn": 16,
                      "textAlign": "LEFT",
                      "dynamicHeight": "AUTO_HEIGHT",
                      "widgetId": "0xmgd40ajs",
                      "minWidth": 450,
                      "isVisible": true,
                      "fontStyle": "BOLD",
                      "textColor": "#71717a",
                      "version": 1,
                      "parentId": "ae8b37mkc3",
                      "renderMode": "CANVAS",
                      "isLoading": false,
                      "responsiveBehavior": "fill",
                      "originalTopRow": 10,
                      "borderRadius": "{{appsmith.theme.borderRadius.appBorderRadius}}",
                      "maxDynamicHeight": 9000,
                      "originalBottomRow": 15,
                      "fontSize": "1rem",
                      "minDynamicHeight": 4
                    },
                    {
                      "widgetName": "cost_sq_ft",
                      "displayName": "Text",
                      "iconSVG": "/static/media/icon.97c59b523e6f70ba6f40a10fc2c7c5b5.svg",
                      "searchTags": [
                        "typography",
                        "paragraph",
                        "label"
                      ],
                      "topRow": 5,
                      "bottomRow": 9,
                      "parentRowSpace": 10,
                      "type": "TEXT_WIDGET",
                      "hideCard": false,
                      "animateLoading": true,
                      "overflow": "NONE",
                      "fontFamily": "{{appsmith.theme.fontFamily.appFont}}",
                      "parentColumnSpace": 10.83154296875,
                      "dynamicTriggerPathList": [],
                      "leftColumn": 42,
                      "dynamicBindingPathList": [
                        {
                          "key": "truncateButtonColor"
                        },
                        {
                          "key": "fontFamily"
                        },
                        {
                          "key": "borderRadius"
                        }
                      ],
                      "shouldTruncate": false,
                      "truncateButtonColor": "{{appsmith.theme.colors.primaryColor}}",
                      "text": "Label",
                      "key": "vi8nsa0y8p",
                      "isDeprecated": false,
                      "rightColumn": 47,
                      "textAlign": "LEFT",
                      "dynamicHeight": "AUTO_HEIGHT",
                      "widgetId": "m43n4kaws6",
                      "minWidth": 450,
                      "isVisible": true,
                      "fontStyle": "BOLD",
                      "textColor": "#71717a",
                      "version": 1,
                      "parentId": "ae8b37mkc3",
                      "renderMode": "CANVAS",
                      "isLoading": false,
                      "responsiveBehavior": "fill",
                      "originalTopRow": 10,
                      "borderRadius": "{{appsmith.theme.borderRadius.appBorderRadius}}",
                      "maxDynamicHeight": 9000,
                      "originalBottomRow": 15,
                      "fontSize": "1rem",
                      "minDynamicHeight": 4
                    },
                    {
                      "widgetName": "appreciation",
                      "displayName": "Text",
                      "iconSVG": "/static/media/icon.97c59b523e6f70ba6f40a10fc2c7c5b5.svg",
                      "searchTags": [
                        "typography",
                        "paragraph",
                        "label"
                      ],
                      "topRow": 9,
                      "bottomRow": 13,
                      "parentRowSpace": 10,
                      "type": "TEXT_WIDGET",
                      "hideCard": false,
                      "animateLoading": true,
                      "overflow": "NONE",
                      "fontFamily": "{{appsmith.theme.fontFamily.appFont}}",
                      "parentColumnSpace": 10.83154296875,
                      "dynamicTriggerPathList": [],
                      "leftColumn": 36,
                      "dynamicBindingPathList": [
                        {
                          "key": "truncateButtonColor"
                        },
                        {
                          "key": "fontFamily"
                        },
                        {
                          "key": "borderRadius"
                        }
                      ],
                      "shouldTruncate": false,
                      "truncateButtonColor": "{{appsmith.theme.colors.primaryColor}}",
                      "text": "Label",
                      "key": "vi8nsa0y8p",
                      "isDeprecated": false,
                      "rightColumn": 41,
                      "textAlign": "LEFT",
                      "dynamicHeight": "AUTO_HEIGHT",
                      "widgetId": "rf7xaj48o0",
                      "minWidth": 450,
                      "isVisible": true,
                      "fontStyle": "BOLD",
                      "textColor": "#71717a",
                      "version": 1,
                      "parentId": "ae8b37mkc3",
                      "renderMode": "CANVAS",
                      "isLoading": false,
                      "responsiveBehavior": "fill",
                      "originalTopRow": 10,
                      "borderRadius": "{{appsmith.theme.borderRadius.appBorderRadius}}",
                      "maxDynamicHeight": 9000,
                      "originalBottomRow": 15,
                      "fontSize": "1rem",
                      "minDynamicHeight": 4
                    }
                  ],
                  "key": "23t0u795pv",
                  "isDeprecated": false,
                  "tabName": "Neighborhood",
                  "rightColumn": 762.40625,
                  "detachFromLayout": true,
                  "widgetId": "ae8b37mkc3",
                  "containerStyle": "none",
                  "minWidth": 450,
                  "isVisible": true,
                  "version": 1,
                  "parentId": "rnxapq94an",
                  "renderMode": "CANVAS",
                  "isLoading": false,
                  "responsiveBehavior": "fill",
                  "flexLayers": []
                },
                {
                  "tabId": "tabkpms8rxioa",
                  "widgetName": "Canvas5",
                  "displayName": "Canvas",
                  "topRow": 1,
                  "bottomRow": 150,
                  "parentRowSpace": 1,
                  "type": "CANVAS_WIDGET",
                  "canExtend": false,
                  "hideCard": true,
                  "minHeight": 190,
                  "parentColumnSpace": 1,
                  "dynamicTriggerPathList": [],
                  "leftColumn": 0,
                  "dynamicBindingPathList": [],
                  "children": [
                    {
                      "widgetName": "tennant_name",
                      "displayName": "Text",
                      "iconSVG": "/static/media/icon.97c59b523e6f70ba6f40a10fc2c7c5b5.svg",
                      "searchTags": [
                        "typography",
                        "paragraph",
                        "label"
                      ],
                      "topRow": 1,
                      "bottomRow": 5,
                      "parentRowSpace": 10,
                      "type": "TEXT_WIDGET",
                      "hideCard": false,
                      "animateLoading": true,
                      "overflow": "NONE",
                      "fontFamily": "{{appsmith.theme.fontFamily.appFont}}",
                      "parentColumnSpace": 10.83154296875,
                      "dynamicTriggerPathList": [],
                      "leftColumn": 1,
                      "dynamicBindingPathList": [
                        {
                          "key": "truncateButtonColor"
                        },
                        {
                          "key": "fontFamily"
                        },
                        {
                          "key": "borderRadius"
                        }
                      ],
                      "shouldTruncate": false,
                      "truncateButtonColor": "{{appsmith.theme.colors.primaryColor}}",
                      "text": "John Dough",
                      "key": "vi8nsa0y8p",
                      "isDeprecated": false,
                      "rightColumn": 17,
                      "textAlign": "LEFT",
                      "dynamicHeight": "AUTO_HEIGHT",
                      "widgetId": "8r08ksotwe",
                      "minWidth": 450,
                      "isVisible": true,
                      "fontStyle": "BOLD",
                      "textColor": "#231F20",
                      "version": 1,
                      "parentId": "gf659w7lzk",
                      "renderMode": "CANVAS",
                      "isLoading": false,
                      "responsiveBehavior": "fill",
                      "borderRadius": "{{appsmith.theme.borderRadius.appBorderRadius}}",
                      "maxDynamicHeight": 9000,
                      "fontSize": "1.25rem",
                      "minDynamicHeight": 4
                    },
                    {
                      "widgetName": "tennant_email_address",
                      "displayName": "Text",
                      "iconSVG": "/static/media/icon.97c59b523e6f70ba6f40a10fc2c7c5b5.svg",
                      "searchTags": [
                        "typography",
                        "paragraph",
                        "label"
                      ],
                      "topRow": 5,
                      "bottomRow": 9,
                      "parentRowSpace": 10,
                      "type": "TEXT_WIDGET",
                      "hideCard": false,
                      "animateLoading": true,
                      "overflow": "NONE",
                      "fontFamily": "{{appsmith.theme.fontFamily.appFont}}",
                      "parentColumnSpace": 10.83154296875,
                      "dynamicTriggerPathList": [],
                      "leftColumn": 1,
                      "dynamicBindingPathList": [
                        {
                          "key": "truncateButtonColor"
                        },
                        {
                          "key": "fontFamily"
                        },
                        {
                          "key": "borderRadius"
                        }
                      ],
                      "shouldTruncate": false,
                      "truncateButtonColor": "{{appsmith.theme.colors.primaryColor}}",
                      "text": "jdough@gmail.com",
                      "key": "vi8nsa0y8p",
                      "isDeprecated": false,
                      "rightColumn": 17,
                      "textAlign": "LEFT",
                      "dynamicHeight": "AUTO_HEIGHT",
                      "widgetId": "2ohyiuoo1d",
                      "minWidth": 450,
                      "isVisible": true,
                      "fontStyle": "BOLD",
                      "textColor": "#71717a",
                      "version": 1,
                      "parentId": "gf659w7lzk",
                      "renderMode": "CANVAS",
                      "isLoading": false,
                      "responsiveBehavior": "fill",
                      "borderRadius": "{{appsmith.theme.borderRadius.appBorderRadius}}",
                      "maxDynamicHeight": 9000,
                      "fontSize": "1rem",
                      "minDynamicHeight": 4
                    },
                    {
                      "widgetName": "tennant_phone_number",
                      "displayName": "Text",
                      "iconSVG": "/static/media/icon.97c59b523e6f70ba6f40a10fc2c7c5b5.svg",
                      "searchTags": [
                        "typography",
                        "paragraph",
                        "label"
                      ],
                      "topRow": 9,
                      "bottomRow": 13,
                      "parentRowSpace": 10,
                      "type": "TEXT_WIDGET",
                      "hideCard": false,
                      "animateLoading": true,
                      "overflow": "NONE",
                      "fontFamily": "{{appsmith.theme.fontFamily.appFont}}",
                      "parentColumnSpace": 10.83154296875,
                      "dynamicTriggerPathList": [],
                      "leftColumn": 1,
                      "dynamicBindingPathList": [
                        {
                          "key": "truncateButtonColor"
                        },
                        {
                          "key": "fontFamily"
                        },
                        {
                          "key": "borderRadius"
                        }
                      ],
                      "shouldTruncate": false,
                      "truncateButtonColor": "{{appsmith.theme.colors.primaryColor}}",
                      "text": "123-456-7890",
                      "key": "vi8nsa0y8p",
                      "isDeprecated": false,
                      "rightColumn": 17,
                      "textAlign": "LEFT",
                      "dynamicHeight": "AUTO_HEIGHT",
                      "widgetId": "cvn8o6zj2r",
                      "minWidth": 450,
                      "isVisible": true,
                      "fontStyle": "BOLD",
                      "textColor": "#71717a",
                      "version": 1,
                      "parentId": "gf659w7lzk",
                      "renderMode": "CANVAS",
                      "isLoading": false,
                      "responsiveBehavior": "fill",
                      "borderRadius": "{{appsmith.theme.borderRadius.appBorderRadius}}",
                      "maxDynamicHeight": 9000,
                      "fontSize": "1rem",
                      "minDynamicHeight": 4
                    },
                    {
                      "widgetName": "tennant_smoking_label",
                      "displayName": "Text",
                      "iconSVG": "/static/media/icon.97c59b523e6f70ba6f40a10fc2c7c5b5.svg",
                      "searchTags": [
                        "typography",
                        "paragraph",
                        "label"
                      ],
                      "topRow": 5,
                      "bottomRow": 9,
                      "parentRowSpace": 10,
                      "type": "TEXT_WIDGET",
                      "hideCard": false,
                      "animateLoading": true,
                      "overflow": "NONE",
                      "fontFamily": "{{appsmith.theme.fontFamily.appFont}}",
                      "parentColumnSpace": 10.83154296875,
                      "dynamicTriggerPathList": [],
                      "leftColumn": 25,
                      "dynamicBindingPathList": [
                        {
                          "key": "truncateButtonColor"
                        },
                        {
                          "key": "fontFamily"
                        },
                        {
                          "key": "borderRadius"
                        }
                      ],
                      "shouldTruncate": false,
                      "truncateButtonColor": "{{appsmith.theme.colors.primaryColor}}",
                      "text": "Smoking Preference:",
                      "key": "vi8nsa0y8p",
                      "isDeprecated": false,
                      "rightColumn": 40,
                      "textAlign": "LEFT",
                      "dynamicHeight": "AUTO_HEIGHT",
                      "widgetId": "yhvhjlby2v",
                      "minWidth": 450,
                      "isVisible": true,
                      "fontStyle": "BOLD",
                      "textColor": "#231F20",
                      "version": 1,
                      "parentId": "gf659w7lzk",
                      "renderMode": "CANVAS",
                      "isLoading": false,
                      "responsiveBehavior": "fill",
                      "borderRadius": "{{appsmith.theme.borderRadius.appBorderRadius}}",
                      "maxDynamicHeight": 9000,
                      "fontSize": "1rem",
                      "minDynamicHeight": 4
                    },
                    {
                      "widgetName": "tennant_smoking",
                      "displayName": "Text",
                      "iconSVG": "/static/media/icon.97c59b523e6f70ba6f40a10fc2c7c5b5.svg",
                      "searchTags": [
                        "typography",
                        "paragraph",
                        "label"
                      ],
                      "topRow": 5,
                      "bottomRow": 9,
                      "parentRowSpace": 10,
                      "type": "TEXT_WIDGET",
                      "hideCard": false,
                      "animateLoading": true,
                      "overflow": "NONE",
                      "fontFamily": "{{appsmith.theme.fontFamily.appFont}}",
                      "parentColumnSpace": 10.83154296875,
                      "dynamicTriggerPathList": [],
                      "leftColumn": 40,
                      "dynamicBindingPathList": [
                        {
                          "key": "truncateButtonColor"
                        },
                        {
                          "key": "fontFamily"
                        },
                        {
                          "key": "borderRadius"
                        }
                      ],
                      "shouldTruncate": false,
                      "truncateButtonColor": "{{appsmith.theme.colors.primaryColor}}",
                      "text": "Label",
                      "key": "vi8nsa0y8p",
                      "isDeprecated": false,
                      "rightColumn": 55,
                      "textAlign": "LEFT",
                      "dynamicHeight": "AUTO_HEIGHT",
                      "widgetId": "ouxi875rzt",
                      "minWidth": 450,
                      "isVisible": true,
                      "fontStyle": "BOLD",
                      "textColor": "#71717a",
                      "version": 1,
                      "parentId": "gf659w7lzk",
                      "renderMode": "CANVAS",
                      "isLoading": false,
                      "responsiveBehavior": "fill",
                      "borderRadius": "{{appsmith.theme.borderRadius.appBorderRadius}}",
                      "maxDynamicHeight": 9000,
                      "fontSize": "1rem",
                      "minDynamicHeight": 4
                    },
                    {
                      "widgetName": "tennant_noise",
                      "displayName": "Text",
                      "iconSVG": "/static/media/icon.97c59b523e6f70ba6f40a10fc2c7c5b5.svg",
                      "searchTags": [
                        "typography",
                        "paragraph",
                        "label"
                      ],
                      "topRow": 9,
                      "bottomRow": 13,
                      "parentRowSpace": 10,
                      "type": "TEXT_WIDGET",
                      "hideCard": false,
                      "animateLoading": true,
                      "overflow": "NONE",
                      "fontFamily": "{{appsmith.theme.fontFamily.appFont}}",
                      "parentColumnSpace": 10.83154296875,
                      "dynamicTriggerPathList": [],
                      "leftColumn": 41,
                      "dynamicBindingPathList": [
                        {
                          "key": "truncateButtonColor"
                        },
                        {
                          "key": "fontFamily"
                        },
                        {
                          "key": "borderRadius"
                        }
                      ],
                      "shouldTruncate": false,
                      "truncateButtonColor": "{{appsmith.theme.colors.primaryColor}}",
                      "text": "Label",
                      "key": "vi8nsa0y8p",
                      "isDeprecated": false,
                      "rightColumn": 56,
                      "textAlign": "LEFT",
                      "dynamicHeight": "AUTO_HEIGHT",
                      "widgetId": "l9mvry870j",
                      "minWidth": 450,
                      "isVisible": true,
                      "fontStyle": "BOLD",
                      "textColor": "#71717a",
                      "version": 1,
                      "parentId": "gf659w7lzk",
                      "renderMode": "CANVAS",
                      "isLoading": false,
                      "responsiveBehavior": "fill",
                      "borderRadius": "{{appsmith.theme.borderRadius.appBorderRadius}}",
                      "maxDynamicHeight": 9000,
                      "fontSize": "1rem",
                      "minDynamicHeight": 4
                    },
                    {
                      "widgetName": "tennant_noise_label",
                      "displayName": "Text",
                      "iconSVG": "/static/media/icon.97c59b523e6f70ba6f40a10fc2c7c5b5.svg",
                      "searchTags": [
                        "typography",
                        "paragraph",
                        "label"
                      ],
                      "topRow": 9,
                      "bottomRow": 13,
                      "parentRowSpace": 10,
                      "type": "TEXT_WIDGET",
                      "hideCard": false,
                      "animateLoading": true,
                      "overflow": "NONE",
                      "fontFamily": "{{appsmith.theme.fontFamily.appFont}}",
                      "parentColumnSpace": 10.83154296875,
                      "dynamicTriggerPathList": [],
                      "leftColumn": 25,
                      "dynamicBindingPathList": [
                        {
                          "key": "truncateButtonColor"
                        },
                        {
                          "key": "fontFamily"
                        },
                        {
                          "key": "borderRadius"
                        }
                      ],
                      "shouldTruncate": false,
                      "truncateButtonColor": "{{appsmith.theme.colors.primaryColor}}",
                      "text": "Predicted Noise Level:",
                      "key": "vi8nsa0y8p",
                      "isDeprecated": false,
                      "rightColumn": 41,
                      "textAlign": "LEFT",
                      "dynamicHeight": "AUTO_HEIGHT",
                      "widgetId": "5237bxi37q",
                      "minWidth": 450,
                      "isVisible": true,
                      "fontStyle": "BOLD",
                      "textColor": "#231F20",
                      "version": 1,
                      "parentId": "gf659w7lzk",
                      "renderMode": "CANVAS",
                      "isLoading": false,
                      "responsiveBehavior": "fill",
                      "originalTopRow": 5,
                      "borderRadius": "{{appsmith.theme.borderRadius.appBorderRadius}}",
                      "maxDynamicHeight": 9000,
                      "originalBottomRow": 10,
                      "fontSize": "1rem",
                      "minDynamicHeight": 4
                    }
                  ],
                  "key": "23t0u795pv",
                  "isDeprecated": false,
                  "tabName": "Tennant Info",
                  "rightColumn": 762.40625,
                  "detachFromLayout": true,
                  "widgetId": "gf659w7lzk",
                  "containerStyle": "none",
                  "minWidth": 450,
                  "isVisible": true,
                  "version": 1,
                  "parentId": "rnxapq94an",
                  "renderMode": "CANVAS",
                  "isLoading": false,
                  "responsiveBehavior": "fill",
                  "flexLayers": []
                }
              ],
              "borderWidth": 1,
              "key": "4y4a0n2w6m",
              "backgroundColor": "#FFFFFF",
              "isDeprecated": false,
              "rightColumn": 61,
              "dynamicHeight": "AUTO_HEIGHT",
              "widgetId": "rnxapq94an",
              "accentColor": "#6b21a8",
              "defaultTab": "Overview",
              "shouldShowTabs": true,
              "minWidth": 450,
              "tabsObj": {
                "tab1": {
                  "label": "Overview",
                  "id": "tab1",
                  "widgetId": "cr8lehxf0j",
                  "isVisible": true,
                  "index": 0,
                  "positioning": "vertical",
                  "isDuplicateLabel": false
                },
                "tab4i4to3lr5y": {
                  "id": "tab4i4to3lr5y",
                  "index": 1,
                  "label": "Market Price",
                  "widgetId": "r4kjenj77t",
                  "isVisible": true,
                  "isDuplicateLabel": false
                },
                "tab00emm8idc2": {
                  "id": "tab00emm8idc2",
                  "index": 2,
                  "label": "Neighborhood",
                  "widgetId": "ae8b37mkc3",
                  "isVisible": true,
                  "isDuplicateLabel": false
                },
                "tabkpms8rxioa": {
                  "id": "tabkpms8rxioa",
                  "index": 3,
                  "label": "Tennant Info",
                  "widgetId": "gf659w7lzk",
                  "isVisible": true,
                  "isDuplicateLabel": false
                }
              },
              "isVisible": true,
              "version": 3,
              "parentId": "0",
              "renderMode": "CANVAS",
              "isLoading": false,
              "responsiveBehavior": "fill",
              "originalTopRow": 14,
              "borderRadius": "{{appsmith.theme.borderRadius.appBorderRadius}}",
              "maxDynamicHeight": 9000,
              "originalBottomRow": 33,
              "minDynamicHeight": 15
            }
          ]
        },
        "layoutOnLoadActions": [],
        "layoutOnLoadActionErrors": [],
        "validOnPageLoadActions": true,
        "id": " Landlord - Apartment Details",
        "deleted": false,
        "policies": [],
        "userPermissions": []
      }
    ],
    "userPermissions": [],
    "policies": [],
    "isHidden": false
  },
  "deleted": false,
  "gitSyncId": "643885a4bbd03e0b8a7eae45_643cb1ee7b609228c2b0ca10"
}